<?xml version="1.0" encoding="utf-8" ?>
<Config>
  <SC01>
    <StartCell>A9</StartCell>
    <DateCell>D5</DateCell>
    <EndCell>备用</EndCell>
    <BottomInfo>         单位负责人：             统计负责人：             填报人：             报出日期：             </BottomInfo>
    <HiddenColumn>0,1,2,3,5,6,7,14</HiddenColumn>
    <HiddenRow>-1</HiddenRow>
  </SC01>


  <SC02>
    <StartCell>A7</StartCell>
    <DateCell>C4</DateCell>
    <EndCell>备用</EndCell>
    <BottomInfo>         单位负责人：             统计负责人：             填报人：             报出日期：             </BottomInfo>
    <HiddenColumn>0,1,2,3,5,6,7,13,14</HiddenColumn>
    <HiddenRow>-1</HiddenRow>
  </SC02>

  <SC03>
    <StartCell>A7</StartCell>
    <DateCell>D4</DateCell>
    <EndCell>备用</EndCell>
    <BottomInfo>         单位负责人：             统计负责人：             填报人：             报出日期：             </BottomInfo>
    <HiddenColumn>0,1,2,3,6,7,12,13</HiddenColumn>
    <HiddenRow>-1</HiddenRow>
  </SC03>

  <SC03_1>
    <StartCell>A7</StartCell>
    <DateCell>D4</DateCell>
    <EndCell>备用</EndCell>
    <BottomInfo>         单位负责人：             统计负责人：             填报人：             报出日期：             </BottomInfo>
    <HiddenColumn>0,1,2,3,6,7,13</HiddenColumn>
    <HiddenRow>-1</HiddenRow>
  </SC03_1>

  <SC04>
    <StartCell>A10</StartCell>
    <DateCell>E5</DateCell>
    <EndCell>备用</EndCell>
    <BottomInfo>         单位负责人：             统计负责人：             填报人：             报出日期：             </BottomInfo>
    <HiddenColumn>0,1,2,3,5,6,7,16</HiddenColumn>
    <HiddenRow>-1</HiddenRow>
  </SC04>

  <SC04_1>
    <StartCell>A10</StartCell>
    <DateCell>E5</DateCell>
    <EndCell>备用</EndCell>
    <BottomInfo>         单位负责人：             统计负责人：             填报人：             报出日期：             </BottomInfo>
    <HiddenColumn>0,1,2,3,5,6,7,16</HiddenColumn>
    <HiddenRow>-1</HiddenRow>
  </SC04_1>
  
  <SC05>
    <StartCell>A9</StartCell>
    <DateCell>G4</DateCell>
    <EndCell>备用</EndCell>
    <BottomInfo>         单位负责人：             统计负责人：             填报人：             报出日期：             </BottomInfo>
    <HiddenColumn>0,1,2,3,5,6,7,22</HiddenColumn>
    <HiddenRow>-1</HiddenRow>
  </SC05>

  <SC06>
    <StartCell>A7</StartCell>
    <DateCell>E4</DateCell>
    <EndCell>备用</EndCell>
    <BottomInfo>         单位负责人：             统计负责人：             填报人：             报出日期：             </BottomInfo>
    <HiddenColumn>0,1,2,3,5,6,7,20,21</HiddenColumn>
    <HiddenRow>-1</HiddenRow>
  </SC06>

  <SC07>
    <StartCell>A8</StartCell>
    <DateCell>E4</DateCell>
    <EndCell>备用</EndCell>
    <BottomInfo>         单位负责人：             统计负责人：             填报人：             报出日期：             </BottomInfo>
    <HiddenColumn>0,1,2,3,5,6,7,19,20</HiddenColumn>
    <HiddenRow>-1</HiddenRow>
  </SC07>

  <SC08>
    <StartCell>A9</StartCell>
    <DateCell>D5</DateCell>
    <EndCell>备用</EndCell>
    <BottomInfo>         单位负责人：             统计负责人：             填报人：             报出日期：             </BottomInfo>
    <HiddenColumn>0,1,2,3,5,6,7,11,18,19</HiddenColumn>
    <HiddenRow>-1</HiddenRow>
  </SC08>

  <SC08_1>
    <StartCell>A9</StartCell>
    <DateCell>D5</DateCell>
    <EndCell>备用</EndCell>
    <BottomInfo>         单位负责人：             统计负责人：             填报人：             报出日期：             </BottomInfo>
    <HiddenColumn>0,1,2,3,5,6,7,11,18,19</HiddenColumn>
    <HiddenRow>-1</HiddenRow>
  </SC08_1>

  <SC09>
    <StartCell>A7</StartCell>
    <DateCell>E4</DateCell>
    <EndCell>备用</EndCell>
    <BottomInfo>         单位负责人：             统计负责人：             填报人：             报出日期：             </BottomInfo>
    <HiddenColumn>0,1,2,3,6,7,17,18,19,20</HiddenColumn>
    <HiddenRow>0,1,2,3,4,5,8,9,10,11,12,13,14,15,17,18</HiddenRow>
  </SC09>

  <SC10>
    <StartCell>A7</StartCell>
    <DateCell>C4</DateCell>
    <EndCell>备用</EndCell>
    <BottomInfo>         单位负责人：             统计负责人：             填报人：             报出日期：             </BottomInfo>
    <HiddenColumn>0,1,2,3,6,7,18,19</HiddenColumn>
    <HiddenRow>-1</HiddenRow>
  </SC10>

  <SC11>
    <StartCell>A12</StartCell>
    <DateCell>J5</DateCell>
    <EndCell>备用</EndCell>
    <BottomInfo>         单位负责人：             统计负责人：             填报人：             报出日期：             </BottomInfo>
    <HiddenColumn>0,1,2,3,6,7,27,28</HiddenColumn>
    <HiddenRow>4,5</HiddenRow>
  </SC11>

  <SC12>
    <StartCell>A9</StartCell>
    <DateCell>D4</DateCell>
    <EndCell>备用</EndCell>
    <BottomInfo>         单位负责人：             统计负责人：             填报人：             报出日期：             </BottomInfo>
    <HiddenColumn>0,1,2,3,5,6,7,8,16,17</HiddenColumn>
    <HiddenRow>-1</HiddenRow>
  </SC12>

  <SC13>
    <StartCell>A9</StartCell>
    <DateCell>E4</DateCell>
    <EndCell>备用</EndCell>
    <BottomInfo>         单位负责人：             统计负责人：             填报人：             报出日期：             </BottomInfo>
    <HiddenColumn>0,1,2,3,6,7,17</HiddenColumn>
    <HiddenRow>-1</HiddenRow>
  </SC13>

  <SC14>
    <StartCell>A7</StartCell>
    <DateCell>C4</DateCell>
    <EndCell>备用</EndCell>
    <BottomInfo>         单位负责人：             统计负责人：             填报人：             报出日期：             </BottomInfo>
    <HiddenColumn>0,1,2,3,5,6,7,14,15</HiddenColumn>
    <HiddenRow>-1</HiddenRow>
  </SC14>


  <SC18>
    <StartCell>A7</StartCell>
    <DateCell>G4</DateCell>
    <EndCell>备用</EndCell>
    <BottomInfo>         单位负责人：             统计负责人：             填报人：             报出日期：             </BottomInfo>
    <HiddenColumn>0,1,2,3,5,6,7,8,27,28</HiddenColumn>
    <HiddenRow>-1</HiddenRow>
  </SC18>

  <SC19>
    <StartCell>A8</StartCell>
    <DateCell>F4</DateCell>
    <EndCell>备用</EndCell>
    <BottomInfo>         单位负责人：             统计负责人：             填报人：             报出日期：             </BottomInfo>
    <HiddenColumn>0,1,2,3,5,6,7,8,23,24</HiddenColumn>
    <HiddenRow>-1</HiddenRow>
  </SC19>

  <SC20>
    <StartCell>A7</StartCell>
    <DateCell>G4</DateCell>
    <EndCell>备用</EndCell>
    <BottomInfo>         单位负责人：             统计负责人：             填报人：             报出日期：             </BottomInfo>
    <HiddenColumn>0,1,2,3,5,6,7,8,29,30</HiddenColumn>
    <HiddenRow>-1</HiddenRow>
  </SC20>

  <SC21>
    <StartCell>A7</StartCell>
    <DateCell>C4</DateCell>
    <EndCell>备用</EndCell>
    <BottomInfo>         单位负责人：             统计负责人：             填报人：             报出日期：             </BottomInfo>
    <HiddenColumn>0,1,2,3,5,6,7,8,15,16</HiddenColumn>
    <HiddenRow>-1</HiddenRow>
  </SC21>

  <SC22>
    <StartCell>A7</StartCell>
    <DateCell>C4</DateCell>
    <EndCell>备用</EndCell>
    <BottomInfo>         单位负责人：             统计负责人：             填报人：             报出日期：             </BottomInfo>
    <HiddenColumn>0,1,2,3,5,6,7,14,15</HiddenColumn>
    <HiddenRow>-1</HiddenRow>
  </SC22>

  <SC23>
    <StartCell>A7</StartCell>
    <DateCell>C4</DateCell>
    <EndCell>备用</EndCell>
    <BottomInfo>         单位负责人：             统计负责人：             填报人：             报出日期：             </BottomInfo>
    <HiddenColumn>0,1,2,3,5,6,7,13,14</HiddenColumn>
    <HiddenRow>-1</HiddenRow>
  </SC23>

  <SC24>
    <StartCell>A7</StartCell>
    <DateCell>C4</DateCell>
    <EndCell>备用</EndCell>
    <BottomInfo>         单位负责人：             统计负责人：             填报人：             报出日期：             </BottomInfo>
    <HiddenColumn>0,1,2,3,6,7,13</HiddenColumn>
    <HiddenRow>-1</HiddenRow>
  </SC24>

  <SC25>
    <StartCell>A7</StartCell>
    <DateCell>C4</DateCell>
    <EndCell>备用</EndCell>
    <BottomInfo>         单位负责人：             统计负责人：             填报人：             报出日期：             </BottomInfo>
    <HiddenColumn>0,1,2,3,5,6,7,13,14</HiddenColumn>
    <HiddenRow>-1</HiddenRow>
  </SC25>

  <SC26>
    <StartCell>A7</StartCell>
    <DateCell>B4</DateCell>
    <EndCell>备用</EndCell>
    <BottomInfo>         单位负责人：             统计负责人：             填报人：             报出日期：             </BottomInfo>
    <HiddenColumn>0,1,2,3,6,7,10,11,12,13,14,15</HiddenColumn>
    <HiddenRow>-1</HiddenRow>
  </SC26>

  <SC27>
    <StartCell>A7</StartCell>
    <DateCell>C4</DateCell>
    <EndCell>备用</EndCell>
    <BottomInfo>         单位负责人：             统计负责人：             填报人：             报出日期：             </BottomInfo>
    <HiddenColumn>0,1,2,3,5,6,7,16,17</HiddenColumn>
    <HiddenRow>-1</HiddenRow>
  </SC27>

  <SC28>
    <StartCell>A8</StartCell>
    <DateCell>F4</DateCell>
    <EndCell>备用</EndCell>
    <BottomInfo>         单位负责人：             统计负责人：             填报人：             报出日期：             </BottomInfo>
    <HiddenColumn>0,1,2,3,4,5,6,7,8,22,23</HiddenColumn>
    <HiddenRow>-1</HiddenRow>
  </SC28>

  <SC28_3>
    <StartCell>A10</StartCell>
    <DateCell>H4</DateCell>
    <EndCell>备用</EndCell>
    <BottomInfo>         单位负责人：             统计负责人：             填报人：             报出日期：             </BottomInfo>
    <HiddenColumn>0,1,2,3,5,6,7,8,32</HiddenColumn>
    <HiddenRow>-1</HiddenRow>
  </SC28_3>

  <SC29>
    <StartCell>A6</StartCell>
    <DateCell>C4</DateCell>
    <EndCell>备用</EndCell>
    <BottomInfo>         单位负责人：             统计负责人：             填报人：             报出日期：             </BottomInfo>
    <HiddenColumn>0,1,2,3,6,7,12,13</HiddenColumn>
    <HiddenRow>-1</HiddenRow>
  </SC29>

  <SC30>
    <StartCell>A8</StartCell>
    <DateCell>C4</DateCell>
    <EndCell>备用</EndCell>
    <BottomInfo>         单位负责人：             统计负责人：             填报人：             报出日期：             </BottomInfo>
    <HiddenColumn>0,1,2,3,5,6,7,8,17,18</HiddenColumn>
    <HiddenRow>-1</HiddenRow>
  </SC30>
  
  <SC31>
    <StartCell>A7</StartCell>
    <DateCell>D5</DateCell>
    <EndCell>备用</EndCell>
    <BottomInfo>         单位负责人：             统计负责人：             填报人：             报出日期：             </BottomInfo>
    <HiddenColumn>0,1,2,3,5,6,7,8,15,16</HiddenColumn>
    <HiddenRow>-1</HiddenRow>
  </SC31>
  
  <SC34>
    <StartCell>A7</StartCell>
    <DateCell>B4</DateCell>
    <EndCell>备用</EndCell>
    <BottomInfo>         单位负责人：             统计负责人：             填报人：             报出日期：             </BottomInfo>
    <HiddenColumn>0,1,2,3,5,6,7,10,11</HiddenColumn>
    <HiddenRow>-1</HiddenRow>
  </SC34>

  <SC35>
    <StartCell>A7</StartCell>
    <DateCell>C4</DateCell>
    <EndCell>备用</EndCell>
    <BottomInfo>         单位负责人：             统计负责人：             填报人：             报出日期：             </BottomInfo>
    <HiddenColumn>1,2,3,4,6,7,8,9,20,21</HiddenColumn>
    <HiddenRow></HiddenRow>
  </SC35>

  <SC36>
    <StartCell>A7</StartCell>
    <DateCell>B4</DateCell>
    <EndCell>备用</EndCell>
    <BottomInfo>         单位负责人：             统计负责人：             填报人：             报出日期：             </BottomInfo>
    <HiddenColumn>0,1,2,3,5,6,7,10,11</HiddenColumn>
    <HiddenRow>-1</HiddenRow>
  </SC36>

  <SC37>
    <StartCell>A6</StartCell>
    <DateCell>C4</DateCell>
    <EndCell>备用</EndCell>
    <BottomInfo>         单位负责人：             统计负责人：             填报人：             报出日期：             </BottomInfo>
    <HiddenColumn>0,1,2,3,8,9</HiddenColumn>
    <HiddenRow>-1</HiddenRow>
  </SC37>

  <SC38>
    <StartCell>A6</StartCell>
    <DateCell>H4</DateCell>
    <EndCell>备用</EndCell>
    <BottomInfo>         单位负责人：             统计负责人：             填报人：             报出日期：             </BottomInfo>
    <HiddenColumn>0,1,2,3,4,5,6,8,23</HiddenColumn>
    <HiddenRow>-1</HiddenRow>
  </SC38>

  <SC39>
    <StartCell>A6</StartCell>
    <DateCell>C4</DateCell>
    <EndCell>备用</EndCell>
    <BottomInfo>         单位负责人：             统计负责人：             填报人：             报出日期：             </BottomInfo>
    <HiddenColumn>0,1,2,3,5,6,7,8,20,21</HiddenColumn>
    <HiddenRow>-1</HiddenRow>
  </SC39>

  <SC40>
    <StartCell>A6</StartCell>
    <DateCell>C4</DateCell>
    <EndCell>备用</EndCell>
    <BottomInfo>         单位负责人：             统计负责人：             填报人：             报出日期：             </BottomInfo>
    <HiddenColumn>0,1,2,3,5,6,7,8,22,23</HiddenColumn>
    <HiddenRow>-1</HiddenRow>
  </SC40>

  <SC41>
    <StartCell>A4</StartCell>
    <DateCell>C4</DateCell>
    <EndCell>备用</EndCell>
    <BottomInfo>         单位负责人：             统计负责人：             填报人：             报出日期：             </BottomInfo>
    <HiddenColumn>0,1,2,3,5,6,7,8,23,24,25</HiddenColumn>
    <HiddenRow>5</HiddenRow>
  </SC41>

  <SC42>
    <StartCell>A8</StartCell>
    <DateCell>D5</DateCell>
    <EndCell>备用</EndCell>
    <BottomInfo>         单位负责人：             统计负责人：             填报人：             报出日期：             </BottomInfo>
    <HiddenColumn>0,1,2,3,5,6,7,15,16</HiddenColumn>
    <HiddenRow>-1</HiddenRow>
  </SC42>

  <SC43>
    <StartCell>A8</StartCell>
    <DateCell>D5</DateCell>
    <EndCell>备用</EndCell>
    <BottomInfo>         单位负责人：             统计负责人：             填报人：             报出日期：             </BottomInfo>
    <HiddenColumn>0,1,2,3,5,6,7,15,16</HiddenColumn>
    <HiddenRow>-1</HiddenRow>
  </SC43>

  <SC44>
    <StartCell>A6</StartCell>
    <DateCell>H2</DateCell>
    <EndCell>备用</EndCell>
    <BottomInfo>         单位负责人：             统计负责人：             填报人：             报出日期：             </BottomInfo>
    <HiddenColumn>0,1,2,3,5,6,7,15,16</HiddenColumn>
    <HiddenRow>-1</HiddenRow>
  </SC44>


  <TG01>
    <StartCell>A7</StartCell>
    <DateCell>C4</DateCell>
    <EndCell>备用</EndCell>
    <BottomInfo>         单位负责人：             统计负责人：             填报人：             报出日期：             </BottomInfo>
    <HiddenColumn>0,1,2,3,6,7,13,14</HiddenColumn>
    <HiddenRow>0</HiddenRow>
  </TG01>

  <TG01_1>
    <StartCell>A7</StartCell>
    <DateCell>C4</DateCell>
    <EndCell>备用</EndCell>
    <BottomInfo>         单位负责人：             统计负责人：             填报人：             报出日期：             </BottomInfo>
    <HiddenColumn>0,1,2,3,6,7,13,14</HiddenColumn>
    <HiddenRow>0</HiddenRow>
  </TG01_1>
  
  <TG03>
    <StartCell>A7</StartCell>
    <DateCell>C4</DateCell>
    <EndCell>备用</EndCell>
    <BottomInfo>         单位负责人：             统计负责人：             填报人：             报出日期：             </BottomInfo>
    <HiddenColumn>0,1,2,3,6,7,13,14</HiddenColumn>
    <HiddenRow>0</HiddenRow>
  </TG03>

  <TG03_1>
    <StartCell>A7</StartCell>
    <DateCell>C4</DateCell>
    <EndCell>备用</EndCell>
    <BottomInfo>         单位负责人：             统计负责人：             填报人：             报出日期：             </BottomInfo>
    <HiddenColumn>0,1,2,3,6,7,13,14</HiddenColumn>
    <HiddenRow>0</HiddenRow>
  </TG03_1>

  <TG04>
    <StartCell>A9</StartCell>
    <DateCell>H4</DateCell>
    <EndCell>备用</EndCell>
    <BottomInfo>         单位负责人：             统计负责人：             填报人：             报出日期：             </BottomInfo>
    <HiddenColumn>0,1,2,3,5,6,7,22,23</HiddenColumn>
    <HiddenRow>-1</HiddenRow>
  </TG04>

  <TG04_2>
    <StartCell>A9</StartCell>
    <DateCell>H4</DateCell>
    <EndCell>备用</EndCell>
    <BottomInfo>         单位负责人：             统计负责人：             填报人：             报出日期：             </BottomInfo>
    <HiddenColumn>0,1,2,3,5,6,7,22,23</HiddenColumn>
    <HiddenRow>-1</HiddenRow>
  </TG04_2>

  <TG07>
    <StartCell>A8</StartCell>
    <DateCell>G5</DateCell>
    <EndCell>备用</EndCell>
    <BottomInfo>         单位负责人：             统计负责人：             填报人：             报出日期：             </BottomInfo>
    <HiddenColumn>0,1,2,3,6,7,19,20</HiddenColumn>
    <HiddenRow>-1</HiddenRow>
  </TG07>

  <TG08_1>
    <StartCell>A8</StartCell>
    <DateCell>G5</DateCell>
    <EndCell>备用</EndCell>
    <BottomInfo>         单位负责人：             统计负责人：             填报人：             报出日期：             </BottomInfo>
    <HiddenColumn>0,1,2,3,6,7,19,20</HiddenColumn>
    <HiddenRow>-1</HiddenRow>
  </TG08_1>

  <TG11>
    <StartCell>A10</StartCell>
    <DateCell>J4</DateCell>
    <EndCell>备用</EndCell>
    <BottomInfo>         单位负责人：             统计负责人：             填报人：             报出日期：             </BottomInfo>
    <HiddenColumn>0,1,2,3,6,7,27,28</HiddenColumn>
    <HiddenRow>39,40</HiddenRow>
  </TG11>

  <TG12>
    <StartCell>A5</StartCell>
    <DateCell>C2</DateCell>
    <EndCell>备用</EndCell>
    <BottomInfo>         单位负责人：             统计负责人：             填报人：             报出日期：             </BottomInfo>
    <HiddenColumn>0,1,2,3,5,6,7,8,16,17</HiddenColumn>
    <HiddenRow>-1</HiddenRow>
  </TG12>

  <TG13>
    <StartCell>A8</StartCell>
    <DateCell>E5</DateCell>
    <EndCell>备用</EndCell>
    <BottomInfo>         单位负责人：             统计负责人：             填报人：             报出日期：             </BottomInfo>
    <HiddenColumn>0,1,2,3,5,6,7,17,18</HiddenColumn>
    <HiddenRow>-1</HiddenRow>
  </TG13>

  <TG13_2>
    <StartCell>A8</StartCell>
    <DateCell>E5</DateCell>
    <EndCell>备用</EndCell>
    <BottomInfo>         单位负责人：             统计负责人：             填报人：             报出日期：             </BottomInfo>
    <HiddenColumn>0,1,2,3,5,6,7,17,18</HiddenColumn>
    <HiddenRow>-1</HiddenRow>
  </TG13_2>

  <TG14>
    <StartCell>A7</StartCell>
    <DateCell>E4</DateCell>
    <EndCell>备用</EndCell>
    <BottomInfo>         单位负责人：             统计负责人：             填报人：             报出日期：             </BottomInfo>
    <HiddenColumn>0,1,2,3,5,6,7,16,17</HiddenColumn>
    <HiddenRow>-1</HiddenRow>
  </TG14>

  <TG18_1>
    <StartCell>A7</StartCell>
    <DateCell>E4</DateCell>
    <EndCell>备用</EndCell>
    <BottomInfo>         单位负责人：             统计负责人：             填报人：             报出日期：             </BottomInfo>
    <HiddenColumn>0,1,2,3,5,6,7,16,17</HiddenColumn>
    <HiddenRow>-1</HiddenRow>
  </TG18_1>

  <TG25_1>
    <StartCell>A7</StartCell>
    <DateCell>C4</DateCell>
    <EndCell>备用</EndCell>
    <BottomInfo>         单位负责人：             统计负责人：             填报人：             报出日期：             </BottomInfo>
    <HiddenColumn>0,1,2,3,5,6,7,15,16</HiddenColumn>
    <HiddenRow>-1</HiddenRow>
  </TG25_1>
  
  <TG26>
    <StartCell>A7</StartCell>
    <DateCell>C4</DateCell>
    <EndCell>备用</EndCell>
    <BottomInfo>         单位负责人：             统计负责人：             填报人：             报出日期：             </BottomInfo>
    <HiddenColumn>0,1,2,3,5,6,7,15,16</HiddenColumn>
    <HiddenRow>-1</HiddenRow>
  </TG26>

  <TG28>
    <StartCell>A7</StartCell>
    <DateCell>F4</DateCell>
    <EndCell>备用</EndCell>
    <BottomInfo>         单位负责人：             统计负责人：             填报人：             报出日期：             </BottomInfo>
    <HiddenColumn>0,1,2,3,6,7,18,19</HiddenColumn>
    <HiddenRow>-1</HiddenRow>
  </TG28>

  <TG28_3>
    <StartCell>A7</StartCell>
    <DateCell>F4</DateCell>
    <EndCell>备用</EndCell>
    <BottomInfo>         单位负责人：             统计负责人：             填报人：             报出日期：             </BottomInfo>
    <HiddenColumn>0,1,2,3,6,7,18,19</HiddenColumn>
    <HiddenRow>-1</HiddenRow>
  </TG28_3>

  <TG29>
    <StartCell>A5</StartCell>
    <DateCell>C2</DateCell>
    <EndCell>备用</EndCell>
    <BottomInfo>         单位负责人：             统计负责人：             填报人：             报出日期：             </BottomInfo>
    <HiddenColumn>0,1,2,3,5,6,7,8,14,15</HiddenColumn>
    <HiddenRow>-1</HiddenRow>
  </TG29>

  <TG30>
    <StartCell>A6</StartCell>
    <DateCell>F4</DateCell>
    <EndCell>备用</EndCell>
    <BottomInfo>         单位负责人：             统计负责人：             填报人：             报出日期：             </BottomInfo>
    <HiddenColumn>0,1,2,3,5,6,7,8,17,18</HiddenColumn>
    <HiddenRow>-1</HiddenRow>
  </TG30>



  <TG37>
    <StartCell>A7</StartCell>
    <DateCell>C4</DateCell>
    <EndCell>备用</EndCell>
    <BottomInfo>         单位负责人：             统计负责人：             填报人：             报出日期：             </BottomInfo>
    <HiddenColumn>0,1,2,3,6,7,12,13</HiddenColumn>
    <HiddenRow>-1</HiddenRow>
  </TG37>

  <TG38>
    <StartCell>A7</StartCell>
    <DateCell>C4</DateCell>
    <EndCell>备用</EndCell>
    <BottomInfo>         单位负责人：             统计负责人：             填报人：             报出日期：             </BottomInfo>
    <HiddenColumn>0,1,2,3,6,7,11,13,14</HiddenColumn>
    <HiddenRow>-1</HiddenRow>
  </TG38>

  <TG39>
    <StartCell>A7</StartCell>
    <DateCell>C4</DateCell>
    <EndCell>备用</EndCell>
    <BottomInfo>         单位负责人：             统计负责人：             填报人：             报出日期：             </BottomInfo>
    <HiddenColumn>0,1,2,3,6,7,11,13,14</HiddenColumn>
    <HiddenRow>-1</HiddenRow>
  </TG39>

  <TG42>
    <StartCell>A7</StartCell>
    <DateCell>F4</DateCell>
    <EndCell>备用</EndCell>
    <BottomInfo>         单位负责人：             统计负责人：             填报人：             报出日期：             </BottomInfo>
    <HiddenColumn>0,1,2,3,6,7,8,20,21</HiddenColumn>
    <HiddenRow>-1</HiddenRow>
  </TG42>

  <TG43>
    <StartCell>A8</StartCell>
    <DateCell>D5</DateCell>
    <EndCell>备用</EndCell>
    <BottomInfo>         单位负责人：             统计负责人：             填报人：             报出日期：             </BottomInfo>
    <HiddenColumn>0,1,2,3,5,6,7,8,17,18</HiddenColumn>
    <HiddenRow>-1</HiddenRow>
  </TG43>

  <TG44>
    <StartCell>A7</StartCell>
    <DateCell>C5</DateCell>
    <EndCell>备用</EndCell>
    <BottomInfo>         单位负责人：             统计负责人：             填报人：             报出日期：             </BottomInfo>
    <HiddenColumn>0,1,2,3,5,6,7,11,12</HiddenColumn>
    <HiddenRow>-1</HiddenRow>
  </TG44>

  <TG45>
    <StartCell>A11</StartCell>
    <DateCell>H6</DateCell>
    <EndCell>备用</EndCell>
    <BottomInfo>         单位负责人：             统计负责人：             填报人：             报出日期：             </BottomInfo>
    <HiddenColumn>0,1,2,3,5,6,7,8,9,25,26</HiddenColumn>
    <HiddenRow>-1</HiddenRow>
  </TG45>

  <TG46>
    <StartCell>A10</StartCell>
    <DateCell>C6</DateCell>
    <EndCell>备用</EndCell>
    <BottomInfo>         单位负责人：             统计负责人：             填报人：             报出日期：             </BottomInfo>
    <HiddenColumn>0,1,2,3,5,6,7,8,9,15,16</HiddenColumn>
    <HiddenRow>-1</HiddenRow>
  </TG46>

  <TG47>
    <StartCell>A10</StartCell>
    <DateCell>C6</DateCell>
    <EndCell>备用</EndCell>
    <BottomInfo>         单位负责人：             统计负责人：             填报人：             报出日期：             </BottomInfo>
    <HiddenColumn>0,1,2,3,5,6,7,8,9,15,16</HiddenColumn>
    <HiddenRow>-1</HiddenRow>
  </TG47>

  <TG48>
    <StartCell>A5</StartCell>
    <DateCell>F2</DateCell>
    <EndCell>备用</EndCell>
    <BottomInfo>         单位负责人：             统计负责人：             填报人：             报出日期：             </BottomInfo>
    <HiddenColumn>0,1,2,3,5,6,7,8,20,21</HiddenColumn>
    <HiddenRow>-1</HiddenRow>
  </TG48>

  <TG49>
    <StartCell>A7</StartCell>
    <DateCell>B4</DateCell>
    <EndCell>备用</EndCell>
    <BottomInfo>         单位负责人：             统计负责人：             填报人：             报出日期：             </BottomInfo>
    <HiddenColumn>0,1,2,3,5,6,7,8,10,11</HiddenColumn>
    <HiddenRow>-1</HiddenRow>
  </TG49>

  <TG50>
    <StartCell>A7</StartCell>
    <DateCell>C5</DateCell>
    <EndCell>备用</EndCell>
    <BottomInfo>         单位负责人：             统计负责人：             填报人：             报出日期：             </BottomInfo>
    <HiddenColumn>0,1,2,3,5,6,7,8,12,13</HiddenColumn>
    <HiddenRow>-1</HiddenRow>
  </TG50>

  <TG51>
    <StartCell>A7</StartCell>
    <DateCell>C5</DateCell>
    <EndCell>备用</EndCell>
    <BottomInfo>         单位负责人：             统计负责人：             填报人：             报出日期：             </BottomInfo>
    <HiddenColumn>0,1,2,3,5,6,7,10,11</HiddenColumn>
    <HiddenRow>-1</HiddenRow>
  </TG51>

  <TG52>
    <StartCell>A9</StartCell>
    <DateCell>H5</DateCell>
    <EndCell>备用</EndCell>
    <BottomInfo>         单位负责人：             统计负责人：             填报人：             报出日期：             </BottomInfo>
    <HiddenColumn>0,1,2,3,5,6,7,20,21</HiddenColumn>
    <HiddenRow>-1</HiddenRow>
  </TG52>

  <TG53>
    <StartCell>A9</StartCell>
    <DateCell>C5</DateCell>
    <EndCell>备用</EndCell>
    <BottomInfo>         单位负责人：             统计负责人：             填报人：             报出日期：             </BottomInfo>
    <HiddenColumn>0,1,2,3,5,6,7,13,14</HiddenColumn>
    <HiddenRow>-1</HiddenRow>
  </TG53>

  <TG54>
    <StartCell>A10</StartCell>
    <DateCell>G5</DateCell>
    <EndCell>备用</EndCell>
    <BottomInfo>         单位负责人：             统计负责人：             填报人：             报出日期：             </BottomInfo>
    <HiddenColumn>0,1,2,3,6,7,20,21</HiddenColumn>
    <HiddenRow>-1</HiddenRow>
  </TG54>

  <TG55>
    <StartCell>A11</StartCell>
    <DateCell>G5</DateCell>
    <EndCell>备用</EndCell>
    <BottomInfo>         单位负责人：             统计负责人：             填报人：             报出日期：             </BottomInfo>
    <HiddenColumn>0,1,2,3,6,7,22,23</HiddenColumn>
    <HiddenRow>-1</HiddenRow>
  </TG55>

  <TG56>
    <StartCell>A11</StartCell>
    <DateCell>G6</DateCell>
    <EndCell>备用</EndCell>
    <BottomInfo>         单位负责人：             统计负责人：             填报人：             报出日期：             </BottomInfo>
    <HiddenColumn>0,1,2,3,5,6,7,18,19</HiddenColumn>
    <HiddenRow>-1</HiddenRow>
  </TG56>

  <TG57>
    <StartCell>A7</StartCell>
    <DateCell>B5</DateCell>
    <EndCell>备用</EndCell>
    <BottomInfo>         单位负责人：             统计负责人：             填报人：             报出日期：             </BottomInfo>
    <HiddenColumn>0,1,2,3,5,6,7,10,11</HiddenColumn>
    <HiddenRow>-1</HiddenRow>
  </TG57>

  <TG58>
    <StartCell>A8</StartCell>
    <DateCell>E5</DateCell>
    <EndCell>备用</EndCell>
    <BottomInfo>         单位负责人：             统计负责人：             填报人：             报出日期：             </BottomInfo>
    <HiddenColumn>0,1,2,3,5,6,7,8,22,23</HiddenColumn>
    <HiddenRow>-1</HiddenRow>
  </TG58>

  <TG59>
    <StartCell>A10</StartCell>
    <DateCell>C5</DateCell>
    <EndCell>备用</EndCell>
    <BottomInfo>         单位负责人：             统计负责人：             填报人：             报出日期：             </BottomInfo>
    <HiddenColumn>0,1,2,3,5,6,7,13,14</HiddenColumn>
    <HiddenRow>-1</HiddenRow>
  </TG59>

  <TG60>
    <StartCell>A7</StartCell>
    <DateCell>C5</DateCell>
    <EndCell>备用</EndCell>
    <BottomInfo>         单位负责人：             统计负责人：             填报人：             报出日期：             </BottomInfo>
    <HiddenColumn>0,1,2,3,5,6,7,12,13</HiddenColumn>
    <HiddenRow>-1</HiddenRow>
  </TG60>

  <TG61>
    <StartCell>A7</StartCell>
    <DateCell>C5</DateCell>
    <EndCell>备用</EndCell>
    <BottomInfo>         单位负责人：             统计负责人：             填报人：             报出日期：             </BottomInfo>
    <HiddenColumn>0,1,2,3,5,6,7,11,12</HiddenColumn>
    <HiddenRow>-1</HiddenRow>
  </TG61>

  <TG62>
    <StartCell>A8</StartCell>
    <DateCell>H5</DateCell>
    <EndCell>备用</EndCell>
    <BottomInfo>         单位负责人：             统计负责人：             填报人：             报出日期：             </BottomInfo>
    <HiddenColumn>0,1,2,3,5,6,7,21,22</HiddenColumn>
    <HiddenRow>-1</HiddenRow>
  </TG62>

  <TG63>
    <StartCell>A8</StartCell>
    <DateCell>B6</DateCell>
    <EndCell>备用</EndCell>
    <BottomInfo>         单位负责人：             统计负责人：             填报人：             报出日期：             </BottomInfo>
    <HiddenColumn>0,1,2,3,5,6,7,10,11</HiddenColumn>
    <HiddenRow>-1</HiddenRow>
  </TG63>

  <TG64>
    <StartCell>A7</StartCell>
    <DateCell>C4</DateCell>
    <EndCell>备用</EndCell>
    <BottomInfo>         单位负责人：             统计负责人：             填报人：             报出日期：             </BottomInfo>

    <HiddenColumn>0,1,2,3,5,6,7,9,20,21</HiddenColumn>
    <HiddenRow>-1</HiddenRow>
  </TG64>

  <TG65>
    <StartCell>A9</StartCell>
    <DateCell>D6</DateCell>
    <EndCell>备用</EndCell>
    <BottomInfo>         单位负责人：             统计负责人：             填报人：             报出日期：             </BottomInfo>
    <HiddenColumn>0,1,2,3,5,6,7,15,16</HiddenColumn>
    <HiddenRow>-1</HiddenRow>
  </TG65>

  <TG66>
    <StartCell>A8</StartCell>
    <DateCell>D5</DateCell>
    <EndCell>备用</EndCell>
    <BottomInfo>         单位负责人：             统计负责人：             填报人：             报出日期：             </BottomInfo>
    <HiddenColumn>0,1,2,3,5,6,7,15,16</HiddenColumn>
    <HiddenRow>-1</HiddenRow>
  </TG66>

  <TG67>
    <StartCell>A10</StartCell>
    <DateCell>H6</DateCell>
    <EndCell>备用</EndCell>
    <BottomInfo>         单位负责人：             统计负责人：             填报人：             报出日期：             </BottomInfo>
    <HiddenColumn>0,1,2,3,5,6,7,8,27,28</HiddenColumn>
    <HiddenRow>-1</HiddenRow>
  </TG67>

  <TG68>
    <StartCell>A11</StartCell>
    <DateCell>G6</DateCell>
    <EndCell>备用</EndCell>
    <BottomInfo>         单位负责人：             统计负责人：             填报人：             报出日期：             </BottomInfo>
    <HiddenColumn>0,1,2,3,5,6,7,8,23,24</HiddenColumn>
    <HiddenRow>-1</HiddenRow>
  </TG68>

  <TG69>
    <StartCell>A10</StartCell>
    <DateCell>H6</DateCell>
    <EndCell>备用</EndCell>
    <BottomInfo>         单位负责人：             统计负责人：             填报人：             报出日期：             </BottomInfo>
    <HiddenColumn>0,1,2,3,5,6,7,8,29,30</HiddenColumn>
    <HiddenRow>-1</HiddenRow>
  </TG69>

  <TG82>
    <StartCell>A10</StartCell>
    <DateCell>H6</DateCell>
    <EndCell>备用</EndCell>
    <BottomInfo>         单位负责人：             统计负责人：             填报人：             报出日期：             </BottomInfo>
    <HiddenColumn>0,1,2,3,5,6,7,8,29,30</HiddenColumn>
    <HiddenRow>-1</HiddenRow>
  </TG82>

  <TG85>
    <StartCell>A10</StartCell>
    <DateCell>H6</DateCell>
    <EndCell>备用</EndCell>
    <BottomInfo>         单位负责人：             统计负责人：             填报人：             报出日期：             </BottomInfo>
    <HiddenColumn>0,1,2,3,5,6,7,8,29,30</HiddenColumn>
    <HiddenRow>-1</HiddenRow>
  </TG85>

  <TG86>
    <StartCell>A10</StartCell>
    <DateCell>H6</DateCell>
    <EndCell>备用</EndCell>
    <BottomInfo>         单位负责人：             统计负责人：             填报人：             报出日期：             </BottomInfo>
    <HiddenColumn>0,1,2,3,5,6,7,8,29,30</HiddenColumn>
    <HiddenRow>-1</HiddenRow>
  </TG86>

  <TG87>
    <StartCell>A10</StartCell>
    <DateCell>H6</DateCell>
    <EndCell>备用</EndCell>
    <BottomInfo>         单位负责人：             统计负责人：             填报人：             报出日期：             </BottomInfo>
    <HiddenColumn>0,1,2,3,5,6,7,8,29,30</HiddenColumn>
    <HiddenRow>-1</HiddenRow>
  </TG87>

  <TG88>
    <StartCell>A10</StartCell>
    <DateCell>H6</DateCell>
    <EndCell>备用</EndCell>
    <BottomInfo>         单位负责人：             统计负责人：             填报人：             报出日期：             </BottomInfo>
    <HiddenColumn>0,1,2,3,5,6,7,8,29,30</HiddenColumn>
    <HiddenRow>-1</HiddenRow>
  </TG88>

  <TG89>
    <StartCell>A10</StartCell>
    <DateCell>H6</DateCell>
    <EndCell>备用</EndCell>
    <BottomInfo>         单位负责人：             统计负责人：             填报人：             报出日期：             </BottomInfo>
    <HiddenColumn>0,1,2,3,5,6,7,8,29,30</HiddenColumn>
    <HiddenRow>-1</HiddenRow>
  </TG89>
  
  <TG90>
    <StartCell>A9</StartCell>
    <DateCell>D6</DateCell>
    <EndCell>备用</EndCell>
    <BottomInfo>         单位负责人：             统计负责人：             填报人：             报出日期：             </BottomInfo>
    <HiddenColumn>0,1,2,3,5,6,7,8,15,16</HiddenColumn>
    <HiddenRow>-1</HiddenRow>
  </TG90>

  
  <NH61>
    <StartCell>A11</StartCell>
    <DateCell>F4</DateCell>
    <EndCell>备用</EndCell>
    <BottomInfo>         单位负责人：             统计负责人：             填报人：             报出日期：             </BottomInfo>
    <HiddenColumn>0,1,3,4</HiddenColumn>
    <HiddenRow>-1</HiddenRow>     
  </NH61>


  <NH62>
    <StartCell>A7</StartCell>
    <DateCell>I3</DateCell>
    <EndCell>备用</EndCell>
    <BottomInfo>         单位负责人：             统计负责人：             填报人：             报出日期：             </BottomInfo>
    <HiddenColumn>0,1,3,4,5</HiddenColumn>
    <HiddenRow>-1</HiddenRow>
  </NH62>


  <NH63>
    <StartCell>A7</StartCell>
    <DateCell>I3</DateCell>
    <EndCell>备用</EndCell>
    <BottomInfo>         单位负责人：             统计负责人：             填报人：             报出日期：             </BottomInfo>
    <HiddenColumn>0,1,3,4,5</HiddenColumn>
    <HiddenRow>-1</HiddenRow>
  </NH63>


  <NH64>
    <StartCell>A7</StartCell>
    <DateCell>F3</DateCell>
    <EndCell>备用</EndCell>
    <BottomInfo>         单位负责人：             统计负责人：             填报人：             报出日期：             </BottomInfo>
    <HiddenColumn>0,1,3,4,5</HiddenColumn>
    <HiddenRow>-1</HiddenRow>
  </NH64>


  <NH65>
    <StartCell>A7</StartCell>
    <DateCell>E3</DateCell>
    <EndCell>备用</EndCell>
    <BottomInfo>         单位负责人：             统计负责人：             填报人：             报出日期：             </BottomInfo>
    <HiddenColumn>0,1,3,4,5</HiddenColumn>
    <HiddenRow>-1</HiddenRow>
  </NH65>


  <NH66>
    <StartCell>A7</StartCell>
    <DateCell>F3</DateCell>
    <EndCell>备用</EndCell>
    <BottomInfo>         单位负责人：             统计负责人：             填报人：             报出日期：             </BottomInfo>
    <HiddenColumn>0,2,3,4,5</HiddenColumn>
    <HiddenRow>-1</HiddenRow>
  </NH66>


  <NH67>
    <StartCell>A7</StartCell>
    <DateCell>C3</DateCell>
    <EndCell>备用</EndCell>
    <BottomInfo>         单位负责人：             统计负责人：             填报人：             报出日期：             </BottomInfo>
    <HiddenColumn>0,1,3,4,6</HiddenColumn>
    <HiddenRow>-1</HiddenRow>
  </NH67>

  <NH68>
    <StartCell>A7</StartCell>
    <DateCell>F3</DateCell>
    <EndCell>备用</EndCell>
    <BottomInfo>         单位负责人：             统计负责人：             填报人：             报出日期：             </BottomInfo>
    <HiddenColumn>0,2,7,12</HiddenColumn>
    <HiddenRow>-1</HiddenRow>
  </NH68>

  <NH70>
    <StartCell>A5</StartCell>
    <DateCell>C3</DateCell>
    <EndCell>备用</EndCell>
    <BottomInfo>         单位负责人：             统计负责人：             填报人：             报出日期：             </BottomInfo>
    <HiddenColumn>-1</HiddenColumn>
    <HiddenRow>-1</HiddenRow>
  </NH70>

  <NH61_ALL>
    <StartCell>A11</StartCell>
    <DateCell>F4</DateCell>
    <EndCell>备用</EndCell>
    <BottomInfo>         单位负责人：             统计负责人：             填报人：             报出日期：             </BottomInfo>
    <HiddenColumn>0,1,3,4</HiddenColumn>
    <HiddenRow>-1</HiddenRow>
  </NH61_ALL>


  <NH62_ALL>
    <StartCell>A7</StartCell>
    <DateCell>I3</DateCell>
    <EndCell>备用</EndCell>
    <BottomInfo>         单位负责人：             统计负责人：             填报人：             报出日期：             </BottomInfo>
    <HiddenColumn>0,1,3,4,5</HiddenColumn>
    <HiddenRow>-1</HiddenRow>
  </NH62_ALL>


  <NH63_ALL>
    <StartCell>A7</StartCell>
    <DateCell>I3</DateCell>
    <EndCell>备用</EndCell>
    <BottomInfo>         单位负责人：             统计负责人：             填报人：             报出日期：             </BottomInfo>
    <HiddenColumn>0,1,3,4,5</HiddenColumn>
    <HiddenRow>-1</HiddenRow>
  </NH63_ALL>


  <NH64_ALL>
    <StartCell>A7</StartCell>
    <DateCell>F3</DateCell>
    <EndCell>备用</EndCell>
    <BottomInfo>         单位负责人：             统计负责人：             填报人：             报出日期：             </BottomInfo>
    <HiddenColumn>0,1,3,4,5</HiddenColumn>
    <HiddenRow>-1</HiddenRow>
  </NH64_ALL>


  <NH65_ALL>
    <StartCell>A7</StartCell>
    <DateCell>E3</DateCell>
    <EndCell>备用</EndCell>
    <BottomInfo>         单位负责人：             统计负责人：             填报人：             报出日期：             </BottomInfo>
    <HiddenColumn>0,1,3,4,5</HiddenColumn>
    <HiddenRow>-1</HiddenRow>
  </NH65_ALL>


  <NH66_ALL>
    <StartCell>A7</StartCell>
    <DateCell>F3</DateCell>
    <EndCell>备用</EndCell>
    <BottomInfo>         单位负责人：             统计负责人：             填报人：             报出日期：             </BottomInfo>
    <HiddenColumn>0,2,3,4,5</HiddenColumn>
    <HiddenRow>-1</HiddenRow>
  </NH66_ALL>


  <NH67_ALL>
    <StartCell>A7</StartCell>
    <DateCell>C3</DateCell>
    <EndCell>备用</EndCell>
    <BottomInfo>         单位负责人：             统计负责人：             填报人：             报出日期：             </BottomInfo>
    <HiddenColumn>0,1,3,4,6</HiddenColumn>
    <HiddenRow>-1</HiddenRow>
  </NH67_ALL>

  <NH68_ALL>
    <StartCell>A7</StartCell>
    <DateCell>F3</DateCell>
    <EndCell>备用</EndCell>
    <BottomInfo>         单位负责人：             统计负责人：             填报人：             报出日期：             </BottomInfo>
    <HiddenColumn>0,2,7,12</HiddenColumn>
    <HiddenRow>-1</HiddenRow>
  </NH68_ALL>

  <NH70_ALL>
    <StartCell>A5</StartCell>
    <DateCell>C3</DateCell>
    <EndCell>备用</EndCell>
    <BottomInfo>         单位负责人：             统计负责人：             填报人：             报出日期：             </BottomInfo>
    <HiddenColumn>-1</HiddenColumn>
    <HiddenRow>-1</HiddenRow>
  </NH70_ALL>

  <H202>
    <StartCell>A5</StartCell>
    <DateCell>C3</DateCell>
    <EndCell>备用</EndCell>
    <BottomInfo>         单位负责人：             统计负责人：             填报人：             报出日期：             </BottomInfo>
    <HiddenColumn>-1</HiddenColumn>
    <HiddenRow>-1</HiddenRow>
  </H202>

  <H000>
    <StartCell>A5</StartCell>
    <DateCell>C3</DateCell>
    <EndCell>备用</EndCell>
    <BottomInfo>         单位负责人：             统计负责人：             填报人：             报出日期：             </BottomInfo>
    <HiddenColumn>-1</HiddenColumn>
    <HiddenRow>-1</HiddenRow>
  </H000>
</Config>